README.md
setup.cfg
setup.py
torch2cmsis/__init__.py
torch2cmsis/converter.py
torch2cmsis/fully_connected_opt_weight_generation.py
torch2cmsis.egg-info/PKG-INFO
torch2cmsis.egg-info/SOURCES.txt
torch2cmsis.egg-info/dependency_links.txt
torch2cmsis.egg-info/not-zip-safe
torch2cmsis.egg-info/requires.txt
torch2cmsis.egg-info/top_level.txt