Metadata-Version: 1.2
Name: torch2cmsis
Version: 0.1
Summary: PyTorch to CMSIS-NN converter
Home-page: https://github.com/BCJuan/torch2cmsis
Author: Juan Borrego Carazo
Author-email: bcjuan@protonmail.com
License: Apache 2.0
Download-URL: https://github.com/BCJuan/torch2cmsis/archive/v_0.1.tar.gz
Keywords: Pytorch,CMSSIS-NN,embedded,neural networks
Platform: UNKNOWN
Classifier: Development Status :: 3 - Alpha
Classifier: Intended Audience :: Developers
Classifier: Topic :: Software Development :: Build Tools
Classifier: License :: OSI Approved :: Apache Software License
Classifier: Programming Language :: Python :: 3
Classifier: Programming Language :: Python :: 3.4
Classifier: Programming Language :: Python :: 3.5
Classifier: Programming Language :: Python :: 3.6
Classifier: Programming Language :: Python :: 3.7
Requires-Python: >=3.6
